Workbook

Sheet Cover
B2: ICICI Bank Ltd
B4: Equity Valuation Model | NSE: ICICIBANK | BSE: 532174 | Sector: Banking
B8: Prepared for: Debjit | Date: 11 June 2026 | Currency: ₹ Crore
A10: Snapshot
B11: Current price (₹) | C11: =Assumptions!B5
B12: Market cap (₹ Cr) | C12: =Assumptions!B7
B13: FY26 net interest income (₹ Cr) | C13: =Historical!I8
B14: FY26 PAT (₹ Cr) | C14: =Historical!I14
B15: Intrinsic value (₹/share) | C15: =Valuation!B19
B16: Upside / (downside) | C16: =Valuation!B21
B17: Implied rating | C17: =Valuation!B22
A20: Contents
B21: 1. Assumptions — all editable drivers (highlighted blue cells)
B22: 2. Historical — FY2019–FY2026 financials
B23: 3. Forecast — FY2027E–FY2031E earnings & book value
B24: 4. Valuation — excess return model & sensitivity
B25: 5. Ratios — returns, margins, growth, leverage
B26: 6. Peer Comps — relative valuation
B29: Disclaimer: For educational/analytical use only. Not investment advice. Figures from public filings; forecasts are illustrative assumptions.

Sheet Assumptions
A1: ICICI Bank Ltd — Key Assumptions & Drivers
A3: All highlighted blue cells are user inputs. ₹ Crore unless stated.
A4: Market Data
A5: Current share price (₹, 06-May-2026) | B5: 1280
A6: Shares outstanding (Crore) | B6: 716
A7: Market capitalisation (₹ Cr) | B7: =B5*B6
A9: Forecast Drivers (FY2027E–FY2031E)
B10: FY2027E | C10: FY2028E | D10: FY2029E | E10: FY2030E | F10: FY2031E
A11: Total asset growth (%) | B11: 0.12 | C11: 0.12 | D11: 0.12 | E11: 0.115 | F11: 0.11
A12: Net interest margin (NII / avg total assets) | B12: 0.0382
A13: Other income growth (%) | B13: 0.1
A14: Opex + provisions (% of total income) | B14: 0.65 | C14: 0.648 | D14: 0.646 | E14: 0.644 | F14: 0.642
A15: Effective tax rate (%) | B15: 0.25
A16: Dividend payout (%) | B16: 0.16
A18: Cost of Equity (CAPM) & Terminal Value
A19: Risk-free rate (10Y G-Sec) | B19: 0.067
A20: Equity beta | B20: 0.75
A21: Equity risk premium | B21: 0.055
A22: Cost of equity = Rf + β × ERP | B22: =B19+B20*B21
A23: Terminal growth rate (g) | B23: 0.055
A25: Legend: | B25: Input | C25: Formula | D25: Link

Sheet Historical
A1: ICICI Bank Ltd — Historical Financials
A3: ₹ Crore, consolidated. Blue = source data. Source: Company filings (consolidated) via Screener.in; FY2026 results announced Apr 2026. Retrieved 11-Jun-2026.
A4: Fiscal Year (ends March) | B4: FY2019 | C4: FY2020 | D4: FY2021 | E4: FY2022 | F4: FY2023 | G4: FY2024 | H4: FY2025 | I4: FY2026
A5: Income Statement
A6: Interest earned | B6: 71982 | C6: 84836 | D6: 89163 | E6: 95407 | F6: 121067 | G6: 159516 | H6: 186331 | I6: 195218
A7: Interest expended | B7: 39178 | C7: 44666 | D7: 42659 | E7: 41167 | F7: 50543 | G7: 74108 | H7: 89028 | I7: 89029
A8: Net interest income (NII) | B8: =B6-B7 | C8: =C6-C7 | D8: =D6-D7 | E8: =E6-E7 | F8: =F6-F7 | G8: =G6-G7 | H8: =H6-H7 | I8: =I6-I7
A9: Other income | B9: 59325 | C9: 64950 | D9: 72174 | E9: 62129 | F9: 65112 | G9: 76522 | H9: 108255 | I9: 116900
A10: Total income (NII + other income) | B10: =B8+B9 | C10: =C8+C9 | D10: =D8+D9 | E10: =E8+E9 | F10: =F8+F9 | G10: =G8+G9 | H10: =H8+H9 | I10: =I8+I9
A11: Operating expenses, provisions & depreciation | B11: 84721 | C11: 86532 | D11: 92649 | E11: 82128 | F11: 89379 | G11: 101495 | H11: 132705 | I11: 146032
A12: Profit before tax | B12: =B10-B11 | C12: =C10-C11 | D12: =D10-D11 | E12: =E10-E11 | F12: =F10-F11 | G12: =G10-G11 | H12: =H10-H11 | I12: =I10-I11
A13: Tax | B13: =B12-B14 | C13: =C12-C14 | D13: =D12-D14 | E13: =E12-E14 | F13: =F12-F14 | G13: =G12-G14 | H13: =H12-H14 | I13: =I12-I14
A14: Profit after tax | B14: 5689 | C14: 11225 | D14: 20364 | E14: 26538 | F14: 35461 | G14: 46081 | H14: 54569 | I14: 57936
A15: EPS (₹) | B15: 6.6 | C15: 14.78 | D15: 26.58 | E15: 36.14 | F15: 48.74 | G15: 63.02 | H15: 71.65 | I15: 75.71
A16: Dividend payout (%) | B16: 0.15 | C16: 0 | D16: 0.08 | E16: 0.14 | F16: 0.16 | G16: 0.16 | H16: 0.15 | I16: 0.16
A18: Balance Sheet
A19: Equity share capital | B19: 1289 | C19: 1295 | D19: 1383 | E19: 1390 | F19: 1397 | G19: 1405 | H19: 1425 | I19: 1432
A20: Reserves & surplus | B20: 112964 | C20: 121665 | D20: 156204 | E20: 180663 | F20: 213101 | G20: 254739 | H20: 312481 | I20: 358946
A21: Net worth | B21: =B19+B20 | C21: =C19+C20 | D21: =D19+D20 | E21: =E19+E20 | F21: =F19+F20 | G21: =G19+G20 | H21: =H19+H20 | I21: =I19+I20
A22: Deposits | B22: 681317 | C22: 800784 | D22: 959940 | E22: 1091366 | F22: 1210832 | G22: 1443580 | H22: 1641637 | I22: 1830020
A23: Borrowings | B23: 210324 | C23: 213852 | D23: 143900 | E23: 161603 | F23: 189062 | G23: 207428 | H23: 218883 | I23: 220264
A24: Other liabilities | B24: 232899 | C24: 239696 | D24: 312385 | E24: 317616 | F24: 344099 | G24: 456911 | H24: 467815 | I24: 503835
A25: Total liabilities & equity | B25: =SUM(B21:B24) | C25: =SUM(C21:C24) | D25: =SUM(D21:D24) | E25: =SUM(E21:E24) | F25: =SUM(F21:F24) | G25: =SUM(G21:G24) | H25: =SUM(H21:H24) | I25: =SUM(I21:I24)
A26: Fixed assets | B26: 9660 | C26: 10409 | D26: 10809 | E26: 10707 | F26: 11070 | G26: 15714 | H26: 24272 | I26: 17420
A27: Investments | B27: 398201 | C27: 443473 | D27: 536579 | E27: 567098 | F27: 639552 | G27: 827163 | H27: 886377 | I27: 870720
A28: Advances & other assets (incl. cash) | B28: 830933 | C28: 923411 | D28: 1026424 | E28: 1174833 | F28: 1307868 | G28: 1521186 | H28: 1731593 | I28: 2026358
A29: Total assets | B29: =SUM(B26:B28) | C29: =SUM(C26:C28) | D29: =SUM(D26:D28) | E29: =SUM(E26:E28) | F29: =SUM(F26:F28) | G29: =SUM(G26:G28) | H29: =SUM(H26:H28) | I29: =SUM(I26:I28)
A30: Balance check (must be ~0) | B30: =B25-B29 | C30: =C25-C29 | D30: =D25-D29 | E30: =E25-E29 | F30: =F25-F29 | G30: =G25-G29 | H30: =H25-H29 | I30: =I25-I29
A32: Key Standalone Metrics, FY2026 (per company release)
A33: Standalone PAT FY26 (₹ Cr) | B33: 50,147 (+6.2% YoY)
A34: Standalone NII FY26 (₹ Cr) | B34: 88,075 (+8.5% YoY)
A35: Net interest margin (Q4 FY26) | B35: 4.32%
A36: Net NPA | B36: 0.33%
A37: Dividend FY26 (₹/share) | B37: 12.0
A38: Advances growth YoY | B38: +15.8%

Sheet Forecast
A1: ICICI Bank Ltd — 5-Year Earnings & Book Value Forecast
A3: ₹ Crore. Drivers feed from Assumptions.
A4: Fiscal Year (ends March) | B4: FY2026A | C4: FY2027E | D4: FY2028E | E4: FY2029E | F4: FY2030E | G4: FY2031E
A5: Total assets | B5: =Historical!I29 | C5: =B5*(1+Assumptions!B11) | D5: =C5*(1+Assumptions!C11) | E5: =D5*(1+Assumptions!D11) | F5: =E5*(1+Assumptions!E11) | G5: =F5*(1+Assumptions!F11)
A6: Average total assets | C6: =(C5+B5)/2 | D6: =(D5+C5)/2 | E6: =(E5+D5)/2 | F6: =(F5+E5)/2 | G6: =(G5+F5)/2
A7: Net interest income (NIM × avg assets) | C7: =C6*Assumptions!$B$12 | D7: =D6*Assumptions!$B$12 | E7: =E6*Assumptions!$B$12 | F7: =F6*Assumptions!$B$12 | G7: =G6*Assumptions!$B$12
A8: Other income | B8: =Historical!I9 | C8: =B8*(1+Assumptions!$B$13) | D8: =C8*(1+Assumptions!$B$13) | E8: =D8*(1+Assumptions!$B$13) | F8: =E8*(1+Assumptions!$B$13) | G8: =F8*(1+Assumptions!$B$13)
A9: Total income | C9: =C7+C8 | D9: =D7+D8 | E9: =E7+E8 | F9: =F7+F8 | G9: =G7+G8
A10: Opex + provisions | C10: =C9*Assumptions!B14 | D10: =D9*Assumptions!C14 | E10: =E9*Assumptions!D14 | F10: =F9*Assumptions!E14 | G10: =G9*Assumptions!F14
A11: Profit before tax | C11: =C9-C10 | D11: =D9-D10 | E11: =E9-E10 | F11: =F9-F10 | G11: =G9-G10
A12: Tax | C12: =C11*Assumptions!$B$15 | D12: =D11*Assumptions!$B$15 | E12: =E11*Assumptions!$B$15 | F12: =F11*Assumptions!$B$15 | G12: =G11*Assumptions!$B$15
A13: Profit after tax | B13: =Historical!I14 | C13: =C11-C12 | D13: =D11-D12 | E13: =E11-E12 | F13: =F11-F12 | G13: =G11-G12
A14: PAT growth (%) | C14: =C13/B13-1 | D14: =D13/C13-1 | E14: =E13/D13-1 | F14: =F13/E13-1 | G14: =G13/F13-1
A15: Dividends paid | C15: =C13*Assumptions!$B$16 | D15: =D13*Assumptions!$B$16 | E15: =E13*Assumptions!$B$16 | F15: =F13*Assumptions!$B$16 | G15: =G13*Assumptions!$B$16
A16: Net worth (BoY + PAT − dividends) | B16: =Historical!I21 | C16: =B16+C13-C15 | D16: =C16+D13-D15 | E16: =D16+E13-E15 | F16: =E16+F13-F15 | G16: =F16+G13-G15
A17: Return on equity (PAT / avg net worth) | C17: =C13/((C16+B16)/2) | D17: =D13/((D16+C16)/2) | E17: =E13/((E16+D16)/2) | F17: =F13/((F16+E16)/2) | G17: =G13/((G16+F16)/2)
A18: Return on assets (PAT / avg assets) | C18: =C13/C6 | D18: =D13/D6 | E18: =E13/E6 | F18: =F13/F6 | G18: =G13/G6
A19: Book value per share (₹) | B19: =B16/Assumptions!$B$6 | C19: =C16/Assumptions!$B$6 | D19: =D16/Assumptions!$B$6 | E19: =E16/Assumptions!$B$6 | F19: =F16/Assumptions!$B$6 | G19: =G16/Assumptions!$B$6

Sheet Valuation
A1: ICICI Bank Ltd — Excess Return (Residual Income) Valuation
A3: Standard for banks: value = current book + PV of returns above cost of equity.
A4: Fiscal Year (ends March) | B4: FY2027E | C4: FY2028E | D4: FY2029E | E4: FY2030E | F4: FY2031E
A5: Beginning net worth | B5: =Forecast!B16 | C5: =Forecast!C16 | D5: =Forecast!D16 | E5: =Forecast!E16 | F5: =Forecast!F16
A6: Profit after tax | B6: =Forecast!C13 | C6: =Forecast!D13 | D6: =Forecast!E13 | E6: =Forecast!F13 | F6: =Forecast!G13
A7: Equity charge (Ke × beginning net worth) | B7: =B5*Assumptions!$B$22 | C7: =C5*Assumptions!$B$22 | D7: =D5*Assumptions!$B$22 | E7: =E5*Assumptions!$B$22 | F7: =F5*Assumptions!$B$22
A8: Excess return | B8: =B6-B7 | C8: =C6-C7 | D8: =D6-D7 | E8: =E6-E7 | F8: =F6-F7
A9: Discount factor @ Ke | B9: =1/(1+Assumptions!$B$22)^1 | C9: =1/(1+Assumptions!$B$22)^2 | D9: =1/(1+Assumptions!$B$22)^3 | E9: =1/(1+Assumptions!$B$22)^4 | F9: =1/(1+Assumptions!$B$22)^5
A10: PV of excess return | B10: =B8*B9 | C10: =C8*C9 | D10: =D8*D9 | E10: =E8*E9 | F10: =F8*F9
A12: Valuation Bridge
A13: Current net worth (FY2026) | B13: =Forecast!B16
A14: Sum of PV of excess returns | B14: =SUM(B10:F10)
A15: Terminal excess return value | B15: =F8*(1+Assumptions!B23)/(Assumptions!B22-Assumptions!B23)
A16: PV of terminal value | B16: =B15*F9
A17: Equity value | B17: =B13+B14+B16
A18: Shares outstanding (Cr) | B18: =Assumptions!B6
A19: Intrinsic value per share (₹) | B19: =B17/B18
A20: Current market price (₹) | B20: =Assumptions!B5
A21: Upside / (downside) | B21: =B19/B20-1
A22: Implied rating | B22: =IF(B21>0.15,"BUY",IF(B21>-0.10,"HOLD","REDUCE"))
A23: Implied P/B (FY26) | B23: =B19/(Forecast!B16/Assumptions!B6)
A25: Sensitivity: Intrinsic Value per Share (₹) — Cost of Equity vs Terminal Growth
A26: Ke ↓ / Terminal g → | B26: 0.045 | C26: 0.05 | D26: 0.055 | E26: 0.06 | F26: 0.065
A27: 0.09825 | B27: =(Forecast!B16+(Forecast!C13-$A27*Forecast!B16)/(1+$A27)^1+(Forecast!D13-$A27*Forecast!C16)/(1+$A27)^2+(Forecast!E13-$A27*Forecast!D16)/(1+$A27)^3+(Forecast!F13-$A27*Forecast!E16)/(1+$A27)^4+(Forecast!G13-$A27*Forecast!F16)/(1+$A27)^5+(Forecast!G13-$A27*Forecast!F16)*(1+B$26)/($A27-B$26)/(1+$A27)^5)/Assumptions!$B$6 | C27: =(Forecast!B16+(Forecast!C13-$A27*Forecast!B16)/(1+$A27)^1+(Forecast!D13-$A27*Forecast!C16)/(1+$A27)^2+(Forecast!E13-$A27*Forecast!D16)/(1+$A27)^3+(Forecast!F13-$A27*Forecast!E16)/(1+$A27)^4+(Forecast!G13-$A27*Forecast!F16)/(1+$A27)^5+(Forecast!G13-$A27*Forecast!F16)*(1+C$26)/($A27-C$26)/(1+$A27)^5)/Assumptions!$B$6 | D27: =(Forecast!B16+(Forecast!C13-$A27*Forecast!B16)/(1+$A27)^1+(Forecast!D13-$A27*Forecast!C16)/(1+$A27)^2+(Forecast!E13-$A27*Forecast!D16)/(1+$A27)^3+(Forecast!F13-$A27*Forecast!E16)/(1+$A27)^4+(Forecast!G13-$A27*Forecast!F16)/(1+$A27)^5+(Forecast!G13-$A27*Forecast!F16)*(1+D$26)/($A27-D$26)/(1+$A27)^5)/Assumptions!$B$6 | E27: =(Forecast!B16+(Forecast!C13-$A27*Forecast!B16)/(1+$A27)^1+(Forecast!D13-$A27*Forecast!C16)/(1+$A27)^2+(Forecast!E13-$A27*Forecast!D16)/(1+$A27)^3+(Forecast!F13-$A27*Forecast!E16)/(1+$A27)^4+(Forecast!G13-$A27*Forecast!F16)/(1+$A27)^5+(Forecast!G13-$A27*Forecast!F16)*(1+E$26)/($A27-E$26)/(1+$A27)^5)/Assumptions!$B$6 | F27: =(Forecast!B16+(Forecast!C13-$A27*Forecast!B16)/(1+$A27)^1+(Forecast!D13-$A27*Forecast!C16)/(1+$A27)^2+(Forecast!E13-$A27*Forecast!D16)/(1+$A27)^3+(Forecast!F13-$A27*Forecast!E16)/(1+$A27)^4+(Forecast!G13-$A27*Forecast!F16)/(1+$A27)^5+(Forecast!G13-$A27*Forecast!F16)*(1+F$26)/($A27-F$26)/(1+$A27)^5)/Assumptions!$B$6
A28: 0.10325 | B28: =(Forecast!B16+(Forecast!C13-$A28*Forecast!B16)/(1+$A28)^1+(Forecast!D13-$A28*Forecast!C16)/(1+$A28)^2+(Forecast!E13-$A28*Forecast!D16)/(1+$A28)^3+(Forecast!F13-$A28*Forecast!E16)/(1+$A28)^4+(Forecast!G13-$A28*Forecast!F16)/(1+$A28)^5+(Forecast!G13-$A28*Forecast!F16)*(1+B$26)/($A28-B$26)/(1+$A28)^5)/Assumptions!$B$6 | C28: =(Forecast!B16+(Forecast!C13-$A28*Forecast!B16)/(1+$A28)^1+(Forecast!D13-$A28*Forecast!C16)/(1+$A28)^2+(Forecast!E13-$A28*Forecast!D16)/(1+$A28)^3+(Forecast!F13-$A28*Forecast!E16)/(1+$A28)^4+(Forecast!G13-$A28*Forecast!F16)/(1+$A28)^5+(Forecast!G13-$A28*Forecast!F16)*(1+C$26)/($A28-C$26)/(1+$A28)^5)/Assumptions!$B$6 | D28: =(Forecast!B16+(Forecast!C13-$A28*Forecast!B16)/(1+$A28)^1+(Forecast!D13-$A28*Forecast!C16)/(1+$A28)^2+(Forecast!E13-$A28*Forecast!D16)/(1+$A28)^3+(Forecast!F13-$A28*Forecast!E16)/(1+$A28)^4+(Forecast!G13-$A28*Forecast!F16)/(1+$A28)^5+(Forecast!G13-$A28*Forecast!F16)*(1+D$26)/($A28-D$26)/(1+$A28)^5)/Assumptions!$B$6 | E28: =(Forecast!B16+(Forecast!C13-$A28*Forecast!B16)/(1+$A28)^1+(Forecast!D13-$A28*Forecast!C16)/(1+$A28)^2+(Forecast!E13-$A28*Forecast!D16)/(1+$A28)^3+(Forecast!F13-$A28*Forecast!E16)/(1+$A28)^4+(Forecast!G13-$A28*Forecast!F16)/(1+$A28)^5+(Forecast!G13-$A28*Forecast!F16)*(1+E$26)/($A28-E$26)/(1+$A28)^5)/Assumptions!$B$6 | F28: =(Forecast!B16+(Forecast!C13-$A28*Forecast!B16)/(1+$A28)^1+(Forecast!D13-$A28*Forecast!C16)/(1+$A28)^2+(Forecast!E13-$A28*Forecast!D16)/(1+$A28)^3+(Forecast!F13-$A28*Forecast!E16)/(1+$A28)^4+(Forecast!G13-$A28*Forecast!F16)/(1+$A28)^5+(Forecast!G13-$A28*Forecast!F16)*(1+F$26)/($A28-F$26)/(1+$A28)^5)/Assumptions!$B$6
A29: 0.10825 | B29: =(Forecast!B16+(Forecast!C13-$A29*Forecast!B16)/(1+$A29)^1+(Forecast!D13-$A29*Forecast!C16)/(1+$A29)^2+(Forecast!E13-$A29*Forecast!D16)/(1+$A29)^3+(Forecast!F13-$A29*Forecast!E16)/(1+$A29)^4+(Forecast!G13-$A29*Forecast!F16)/(1+$A29)^5+(Forecast!G13-$A29*Forecast!F16)*(1+B$26)/($A29-B$26)/(1+$A29)^5)/Assumptions!$B$6 | C29: =(Forecast!B16+(Forecast!C13-$A29*Forecast!B16)/(1+$A29)^1+(Forecast!D13-$A29*Forecast!C16)/(1+$A29)^2+(Forecast!E13-$A29*Forecast!D16)/(1+$A29)^3+(Forecast!F13-$A29*Forecast!E16)/(1+$A29)^4+(Forecast!G13-$A29*Forecast!F16)/(1+$A29)^5+(Forecast!G13-$A29*Forecast!F16)*(1+C$26)/($A29-C$26)/(1+$A29)^5)/Assumptions!$B$6 | D29: =(Forecast!B16+(Forecast!C13-$A29*Forecast!B16)/(1+$A29)^1+(Forecast!D13-$A29*Forecast!C16)/(1+$A29)^2+(Forecast!E13-$A29*Forecast!D16)/(1+$A29)^3+(Forecast!F13-$A29*Forecast!E16)/(1+$A29)^4+(Forecast!G13-$A29*Forecast!F16)/(1+$A29)^5+(Forecast!G13-$A29*Forecast!F16)*(1+D$26)/($A29-D$26)/(1+$A29)^5)/Assumptions!$B$6 | E29: =(Forecast!B16+(Forecast!C13-$A29*Forecast!B16)/(1+$A29)^1+(Forecast!D13-$A29*Forecast!C16)/(1+$A29)^2+(Forecast!E13-$A29*Forecast!D16)/(1+$A29)^3+(Forecast!F13-$A29*Forecast!E16)/(1+$A29)^4+(Forecast!G13-$A29*Forecast!F16)/(1+$A29)^5+(Forecast!G13-$A29*Forecast!F16)*(1+E$26)/($A29-E$26)/(1+$A29)^5)/Assumptions!$B$6 | F29: =(Forecast!B16+(Forecast!C13-$A29*Forecast!B16)/(1+$A29)^1+(Forecast!D13-$A29*Forecast!C16)/(1+$A29)^2+(Forecast!E13-$A29*Forecast!D16)/(1+$A29)^3+(Forecast!F13-$A29*Forecast!E16)/(1+$A29)^4+(Forecast!G13-$A29*Forecast!F16)/(1+$A29)^5+(Forecast!G13-$A29*Forecast!F16)*(1+F$26)/($A29-F$26)/(1+$A29)^5)/Assumptions!$B$6
A30: 0.11325 | B30: =(Forecast!B16+(Forecast!C13-$A30*Forecast!B16)/(1+$A30)^1+(Forecast!D13-$A30*Forecast!C16)/(1+$A30)^2+(Forecast!E13-$A30*Forecast!D16)/(1+$A30)^3+(Forecast!F13-$A30*Forecast!E16)/(1+$A30)^4+(Forecast!G13-$A30*Forecast!F16)/(1+$A30)^5+(Forecast!G13-$A30*Forecast!F16)*(1+B$26)/($A30-B$26)/(1+$A30)^5)/Assumptions!$B$6 | C30: =(Forecast!B16+(Forecast!C13-$A30*Forecast!B16)/(1+$A30)^1+(Forecast!D13-$A30*Forecast!C16)/(1+$A30)^2+(Forecast!E13-$A30*Forecast!D16)/(1+$A30)^3+(Forecast!F13-$A30*Forecast!E16)/(1+$A30)^4+(Forecast!G13-$A30*Forecast!F16)/(1+$A30)^5+(Forecast!G13-$A30*Forecast!F16)*(1+C$26)/($A30-C$26)/(1+$A30)^5)/Assumptions!$B$6 | D30: =(Forecast!B16+(Forecast!C13-$A30*Forecast!B16)/(1+$A30)^1+(Forecast!D13-$A30*Forecast!C16)/(1+$A30)^2+(Forecast!E13-$A30*Forecast!D16)/(1+$A30)^3+(Forecast!F13-$A30*Forecast!E16)/(1+$A30)^4+(Forecast!G13-$A30*Forecast!F16)/(1+$A30)^5+(Forecast!G13-$A30*Forecast!F16)*(1+D$26)/($A30-D$26)/(1+$A30)^5)/Assumptions!$B$6 | E30: =(Forecast!B16+(Forecast!C13-$A30*Forecast!B16)/(1+$A30)^1+(Forecast!D13-$A30*Forecast!C16)/(1+$A30)^2+(Forecast!E13-$A30*Forecast!D16)/(1+$A30)^3+(Forecast!F13-$A30*Forecast!E16)/(1+$A30)^4+(Forecast!G13-$A30*Forecast!F16)/(1+$A30)^5+(Forecast!G13-$A30*Forecast!F16)*(1+E$26)/($A30-E$26)/(1+$A30)^5)/Assumptions!$B$6 | F30: =(Forecast!B16+(Forecast!C13-$A30*Forecast!B16)/(1+$A30)^1+(Forecast!D13-$A30*Forecast!C16)/(1+$A30)^2+(Forecast!E13-$A30*Forecast!D16)/(1+$A30)^3+(Forecast!F13-$A30*Forecast!E16)/(1+$A30)^4+(Forecast!G13-$A30*Forecast!F16)/(1+$A30)^5+(Forecast!G13-$A30*Forecast!F16)*(1+F$26)/($A30-F$26)/(1+$A30)^5)/Assumptions!$B$6
A31: 0.11825 | B31: =(Forecast!B16+(Forecast!C13-$A31*Forecast!B16)/(1+$A31)^1+(Forecast!D13-$A31*Forecast!C16)/(1+$A31)^2+(Forecast!E13-$A31*Forecast!D16)/(1+$A31)^3+(Forecast!F13-$A31*Forecast!E16)/(1+$A31)^4+(Forecast!G13-$A31*Forecast!F16)/(1+$A31)^5+(Forecast!G13-$A31*Forecast!F16)*(1+B$26)/($A31-B$26)/(1+$A31)^5)/Assumptions!$B$6 | C31: =(Forecast!B16+(Forecast!C13-$A31*Forecast!B16)/(1+$A31)^1+(Forecast!D13-$A31*Forecast!C16)/(1+$A31)^2+(Forecast!E13-$A31*Forecast!D16)/(1+$A31)^3+(Forecast!F13-$A31*Forecast!E16)/(1+$A31)^4+(Forecast!G13-$A31*Forecast!F16)/(1+$A31)^5+(Forecast!G13-$A31*Forecast!F16)*(1+C$26)/($A31-C$26)/(1+$A31)^5)/Assumptions!$B$6 | D31: =(Forecast!B16+(Forecast!C13-$A31*Forecast!B16)/(1+$A31)^1+(Forecast!D13-$A31*Forecast!C16)/(1+$A31)^2+(Forecast!E13-$A31*Forecast!D16)/(1+$A31)^3+(Forecast!F13-$A31*Forecast!E16)/(1+$A31)^4+(Forecast!G13-$A31*Forecast!F16)/(1+$A31)^5+(Forecast!G13-$A31*Forecast!F16)*(1+D$26)/($A31-D$26)/(1+$A31)^5)/Assumptions!$B$6 | E31: =(Forecast!B16+(Forecast!C13-$A31*Forecast!B16)/(1+$A31)^1+(Forecast!D13-$A31*Forecast!C16)/(1+$A31)^2+(Forecast!E13-$A31*Forecast!D16)/(1+$A31)^3+(Forecast!F13-$A31*Forecast!E16)/(1+$A31)^4+(Forecast!G13-$A31*Forecast!F16)/(1+$A31)^5+(Forecast!G13-$A31*Forecast!F16)*(1+E$26)/($A31-E$26)/(1+$A31)^5)/Assumptions!$B$6 | F31: =(Forecast!B16+(Forecast!C13-$A31*Forecast!B16)/(1+$A31)^1+(Forecast!D13-$A31*Forecast!C16)/(1+$A31)^2+(Forecast!E13-$A31*Forecast!D16)/(1+$A31)^3+(Forecast!F13-$A31*Forecast!E16)/(1+$A31)^4+(Forecast!G13-$A31*Forecast!F16)/(1+$A31)^5+(Forecast!G13-$A31*Forecast!F16)*(1+F$26)/($A31-F$26)/(1+$A31)^5)/Assumptions!$B$6

Sheet Ratios
A1: ICICI Bank Ltd — Ratio & Trend Analysis
A3: Computed from Historical sheet.
A4: Fiscal Year (ends March) | B4: FY2019 | C4: FY2020 | D4: FY2021 | E4: FY2022 | F4: FY2023 | G4: FY2024 | H4: FY2025 | I4: FY2026
A5: NII growth (%) | B5: — | C5: =Historical!C8/Historical!B8-1 | D5: =Historical!D8/Historical!C8-1 | E5: =Historical!E8/Historical!D8-1 | F5: =Historical!F8/Historical!E8-1 | G5: =Historical!G8/Historical!F8-1 | H5: =Historical!H8/Historical!G8-1 | I5: =Historical!I8/Historical!H8-1
A6: PAT growth (%) | B6: — | C6: =Historical!C14/Historical!B14-1 | D6: =Historical!D14/Historical!C14-1 | E6: =Historical!E14/Historical!D14-1 | F6: =Historical!F14/Historical!E14-1 | G6: =Historical!G14/Historical!F14-1 | H6: =Historical!H14/Historical!G14-1 | I6: =Historical!I14/Historical!H14-1
A7: NIM proxy (NII / avg total assets) | B7: =Historical!B8/Historical!B29 | C7: =Historical!C8/((Historical!C29+Historical!B29)/2) | D7: =Historical!D8/((Historical!D29+Historical!C29)/2) | E7: =Historical!E8/((Historical!E29+Historical!D29)/2) | F7: =Historical!F8/((Historical!F29+Historical!E29)/2) | G7: =Historical!G8/((Historical!G29+Historical!F29)/2) | H7: =Historical!H8/((Historical!H29+Historical!G29)/2) | I7: =Historical!I8/((Historical!I29+Historical!H29)/2)
A8: Other income / total income | B8: =Historical!B9/Historical!B10 | C8: =Historical!C9/Historical!C10 | D8: =Historical!D9/Historical!D10 | E8: =Historical!E9/Historical!E10 | F8: =Historical!F9/Historical!F10 | G8: =Historical!G9/Historical!G10 | H8: =Historical!H9/Historical!H10 | I8: =Historical!I9/Historical!I10
A9: Cost ratio (opex+prov / total income) | B9: =Historical!B11/Historical!B10 | C9: =Historical!C11/Historical!C10 | D9: =Historical!D11/Historical!D10 | E9: =Historical!E11/Historical!E10 | F9: =Historical!F11/Historical!F10 | G9: =Historical!G11/Historical!G10 | H9: =Historical!H11/Historical!H10 | I9: =Historical!I11/Historical!I10
A10: Return on assets (PAT / avg assets) | B10: =Historical!B14/Historical!B29 | C10: =Historical!C14/((Historical!C29+Historical!B29)/2) | D10: =Historical!D14/((Historical!D29+Historical!C29)/2) | E10: =Historical!E14/((Historical!E29+Historical!D29)/2) | F10: =Historical!F14/((Historical!F29+Historical!E29)/2) | G10: =Historical!G14/((Historical!G29+Historical!F29)/2) | H10: =Historical!H14/((Historical!H29+Historical!G29)/2) | I10: =Historical!I14/((Historical!I29+Historical!H29)/2)
A11: Return on equity (PAT / avg net worth) | B11: =Historical!B14/Historical!B21 | C11: =Historical!C14/((Historical!C21+Historical!B21)/2) | D11: =Historical!D14/((Historical!D21+Historical!C21)/2) | E11: =Historical!E14/((Historical!E21+Historical!D21)/2) | F11: =Historical!F14/((Historical!F21+Historical!E21)/2) | G11: =Historical!G14/((Historical!G21+Historical!F21)/2) | H11: =Historical!H14/((Historical!H21+Historical!G21)/2) | I11: =Historical!I14/((Historical!I21+Historical!H21)/2)
A12: Deposit growth (%) | B12: — | C12: =Historical!C22/Historical!B22-1 | D12: =Historical!D22/Historical!C22-1 | E12: =Historical!E22/Historical!D22-1 | F12: =Historical!F22/Historical!E22-1 | G12: =Historical!G22/Historical!F22-1 | H12: =Historical!H22/Historical!G22-1 | I12: =Historical!I22/Historical!H22-1
A13: Asset growth (%) | B13: — | C13: =Historical!C29/Historical!B29-1 | D13: =Historical!D29/Historical!C29-1 | E13: =Historical!E29/Historical!D29-1 | F13: =Historical!F29/Historical!E29-1 | G13: =Historical!G29/Historical!F29-1 | H13: =Historical!H29/Historical!G29-1 | I13: =Historical!I29/Historical!H29-1
A14: Book value per share (₹) | B14: =Historical!B21/Assumptions!$B$6 | C14: =Historical!C21/Assumptions!$B$6 | D14: =Historical!D21/Assumptions!$B$6 | E14: =Historical!E21/Assumptions!$B$6 | F14: =Historical!F21/Assumptions!$B$6 | G14: =Historical!G21/Assumptions!$B$6 | H14: =Historical!H21/Assumptions!$B$6 | I14: =Historical!I21/Assumptions!$B$6
A15: Leverage (assets / net worth, x) | B15: =Historical!B29/Historical!B21 | C15: =Historical!C29/Historical!C21 | D15: =Historical!D29/Historical!D21 | E15: =Historical!E29/Historical!E21 | F15: =Historical!F29/Historical!F21 | G15: =Historical!G29/Historical!G21 | H15: =Historical!H29/Historical!H21 | I15: =Historical!I29/Historical!I21

Sheet Peer Comps
A1: ICICI Bank Ltd — Peer Comparison (Indian Banks)
A3: Blue = inputs (as researched, Jun 2026). Yellow = update with live data.
A4: Bank | B4: Price (₹) | C4: EPS FY26 (₹) | D4: BVPS (₹) | E4: PAT FY26 (₹ Cr) | F4: P/E (x) | G4: P/B (x)
A5: ICICI Bank | B5: 1280 | C5: 75.71 | D5: 503 | E5: 57936 | F5: =IF(C5>0,B5/C5,"n/a") | G5: =IF(D5>0,B5/D5,"n/a")
A6: HDFC Bank | B6: 747.05 | C6: 49.39 | D6: 378 | E6: 79219 | F6: =IF(C6>0,B6/C6,"n/a") | G6: =IF(D6>0,B6/D6,"n/a")
A7: Kotak Mahindra Bank | B7: 2000 | C7: 95 | D7: 784 | F7: =IF(C7>0,B7/C7,"n/a") | G7: =IF(D7>0,B7/D7,"n/a")
A8: Axis Bank | B8: 1352.9 | C8: 96 | D8: 680 | F8: =IF(C8>0,B8/C8,"n/a") | G8: =IF(D8>0,B8/D8,"n/a")
A9: State Bank of India | B9: 1004.1 | C9: 92 | D9: 702 | F9: =IF(C9>0,B9/C9,"n/a") | G9: =IF(D9>0,B9/D9,"n/a")
A12: MARKET APPROACH — COMPARABLE COMPANY ANALYSIS
A13: Peer median P/E (x) | B13: =MEDIAN(F6:F9)
A14: Peer median P/B (x) | B14: =MEDIAN(G6:G9)
A15: Implied value — median P/B × FY26 BVPS (₹) | B15: =B14*D5
A17: VALUATION TRIANGULATION — FOOTBALL FIELD
A18: Method | B18: Low (₹) | C18: Base (₹) | D18: High (₹)
A19: Excess-return / RI | B19: =Valuation!B19*0.9 | C19: =Valuation!B19 | D19: =Valuation!B19*1.1
A20: Comparable companies | B20: =B15*0.9 | C20: =B15 | D20: =B15*1.1
A21: Blended target (70% intrinsic / 30% comps) | C21: =0.7*Valuation!B19+0.3*B15
A22: Current market price (₹) | C22: =B5
A23: Implied upside / (downside) | C23: =C21/B5-1
A25: Peer multiples researched as of Jun 2026 (Kotak price to be verified). Refresh peer inputs before publication.
