Workbook

Sheet Cover
B2: Tata Consultancy Services Ltd
B4: Equity Valuation Model | NSE: TCS | BSE: 532540 | Sector: IT Services
B8: Prepared for: Debjit | Date: 11 June 2026 | Currency: ₹ Crore
A10: Snapshot
B11: Current price (₹) | C11: =Assumptions!B5
B12: Market cap (₹ Cr) | C12: =Assumptions!B7
B13: FY26 revenue (₹ Cr) | C13: =Historical!I6
B14: FY26 PAT (₹ Cr) | C14: =Historical!I17
B15: Intrinsic value (₹/share) | C15: =DCF!B18
B16: Upside / (downside) | C16: =DCF!B20
B17: Implied rating | C17: =DCF!B21
A20: Contents
B21: 1. Assumptions — all editable drivers (highlighted blue cells)
B22: 2. Historical — FY2019–FY2026 income statement, balance sheet, cash flow
B23: 3. Forecast — FY2027E–FY2031E operating model & FCFF build
B24: 4. DCF — valuation bridge & WACC/growth sensitivity
B25: 5. Ratios — margins, returns, conversion, leverage
B26: 6. Peer Comps — relative valuation
B29: Disclaimer: For educational/analytical use only. Not investment advice. Figures from public filings; forecasts are illustrative assumptions.

Sheet Assumptions
A1: Tata Consultancy Services Ltd — Key Assumptions & Drivers
A3: All highlighted blue cells are user inputs. ₹ Crore unless stated.
A4: Market Data
A5: Current share price (₹, 18-Jul-2026) | B5: 2190
A6: Shares outstanding (Crore) | B6: 362
A7: Market capitalisation (₹ Cr) | B7: =B5*B6
A8: Net debt / (net cash) (₹ Cr) | B8: -22705
A9: Note: net debt = borrowings less investments (proxy for cash & equivalents)
A11: Operating Forecast Drivers (FY2027E–FY2031E)
B12: FY2027E | C12: FY2028E | D12: FY2029E | E12: FY2030E | F12: FY2031E
A13: Revenue growth (%) | B13: 0.06 | C13: 0.065 | D13: 0.07 | E13: 0.07 | F13: 0.065
A14: EBITDA margin (%) | B14: 0.272 | C14: 0.272 | D14: 0.273 | E14: 0.274 | F14: 0.275
A15: Depreciation & amortisation (% of revenue) | B15: 0.021
A16: Capex (% of revenue) | B16: 0.016
A17: Effective tax rate (%) | B17: 0.25
A18: Incr. working capital (% of incremental revenue) | B18: 0.12
A20: Cost of Capital (CAPM)
A21: Risk-free rate (10Y G-Sec) | B21: 0.067
A22: Equity beta | B22: 0.85
A23: Equity risk premium | B23: 0.055
A24: Cost of equity = Rf + β × ERP | B24: =B21+B22*B23
A25: WACC (≈ cost of equity; negligible debt) | B25: =B24
A26: Terminal growth rate (g) | B26: 0.05
A28: Legend: | B28: Input | C28: Formula | D28: Link

Sheet Historical
A1: Tata Consultancy Services Ltd — Historical Financials
A3: ₹ Crore, consolidated. Blue = source data. Source: Company filings (consolidated) via Screener.in; FY2026 results announced Apr 2026. Retrieved 11-Jun-2026.
A4: Fiscal Year (ends March) | B4: FY2019 | C4: FY2020 | D4: FY2021 | E4: FY2022 | F4: FY2023 | G4: FY2024 | H4: FY2025 | I4: FY2026
A5: Income Statement
A6: Revenue | B6: 146463 | C6: 156949 | D6: 164177 | E6: 191754 | F6: 225458 | G6: 240893 | H6: 255324 | I6: 267021
A7: Revenue growth (%) | C7: =D6/C6-1 | D7: =E6/D6-1 | E7: =F6/E6-1 | F7: =G6/F6-1 | G7: =H6/G6-1 | H7: =I6/H6-1 | I7: =J6/I6-1
A8: Operating expenses | B8: 106957 | C8: 114840 | D8: 117631 | E8: 138697 | F8: 166199 | G8: 176597 | H8: 187917 | I8: 194623
A9: EBITDA | B9: =B6-B8 | C9: =C6-C8 | D9: =D6-D8 | E9: =E6-E8 | F9: =F6-F8 | G9: =G6-G8 | H9: =H6-H8 | I9: =I6-I8
A10: EBITDA margin (%) | B10: =B9/B6 | C10: =C9/C6 | D10: =D9/D6 | E10: =E9/E6 | F10: =F9/F6 | G10: =G9/G6 | H10: =H9/H6 | I10: =I9/I6
A11: Depreciation & amortisation | B11: 2056 | C11: 3529 | D11: 4065 | E11: 4604 | F11: 5022 | G11: 4985 | H11: 5242 | I11: 5560
A12: EBIT | B12: =B9-B11 | C12: =C9-C11 | D12: =D9-D11 | E12: =E9-E11 | F12: =F9-F11 | G12: =G9-G11 | H12: =H9-H11 | I12: =I9-I11
A13: Other income | B13: 4311 | C13: 4592 | D13: 1916 | E13: 4018 | F13: 3449 | G13: 3464 | H13: 3962 | I13: -124
A14: Finance costs | B14: 198 | C14: 924 | D14: 637 | E14: 784 | F14: 779 | G14: 778 | H14: 796 | I14: 1227
A15: Profit before tax | B15: =B12+B13-B14 | C15: =C12+C13-C14 | D15: =D12+D13-D14 | E15: =E12+E13-E14 | F15: =F12+F13-F14 | G15: =G12+G13-G14 | H15: =H12+H13-H14 | I15: =I12+I13-I14
A16: Tax | B16: =B15-B17 | C16: =C15-C17 | D16: =D15-D17 | E16: =E15-E17 | F16: =F15-F17 | G16: =G15-G17 | H16: =H15-H17 | I16: =I15-I17
A17: Profit after tax | B17: 31562 | C17: 32447 | D17: 32562 | E17: 38449 | F17: 42303 | G17: 46099 | H17: 48797 | I17: 49454
A18: PAT margin (%) | B18: =B17/B6 | C18: =C17/C6 | D18: =D17/D6 | E18: =E17/E6 | F18: =F17/F6 | G18: =G17/G6 | H18: =H17/H6 | I18: =I17/I6
A19: EPS (₹) | B19: 83.87 | C19: 86.19 | D19: 87.67 | E19: 104.75 | F19: 115.19 | G19: 126.88 | H19: 134.2 | I19: 136.01
A20: Dividend payout (%) | B20: 0.36 | C20: 0.85 | D20: 0.43 | E20: 0.41 | F20: 1 | G20: 0.58 | H20: 0.94 | I20: 0.81
A22: Balance Sheet
A23: Equity share capital | B23: 375 | C23: 375 | D23: 370 | E23: 366 | F23: 366 | G23: 362 | H23: 362 | I23: 362
A24: Reserves & surplus | B24: 89071 | C24: 83751 | D24: 86063 | E24: 88773 | F24: 90058 | G24: 90127 | H24: 94394 | I24: 106878
A25: Net worth | B25: =B23+B24 | C25: =C23+C24 | D25: =D23+D24 | E25: =E23+E24 | F25: =F23+F24 | G25: =G23+G24 | H25: =H23+H24 | I25: =I23+I24
A26: Borrowings (incl. lease liabilities) | B26: 62 | C26: 8174 | D26: 7795 | E26: 7818 | F26: 7688 | G26: 8021 | H26: 9392 | I26: 11283
A27: Other liabilities & provisions | B27: 24393 | C27: 27827 | D27: 35764 | E27: 43967 | F27: 44747 | G27: 46962 | H27: 54501 | I27: 62644
A28: Total equity & liabilities | B28: =B25+B26+B27 | C28: =C25+C26+C27 | D28: =D25+D26+D27 | E28: =E25+E26+E27 | F28: =F25+F26+F27 | G28: =G25+G26+G27 | H28: =H25+H26+H27 | I28: =I25+I26+I27
A29: Fixed assets (net) | B29: 12290 | C29: 20928 | D29: 21021 | E29: 21298 | F29: 20515 | G29: 19604 | H29: 23053 | I29: 31343
A30: Capital work-in-progress | B30: 963 | C30: 906 | D30: 926 | E30: 1205 | F30: 1234 | G30: 1564 | H30: 1546 | I30: 2665
A31: Investments | B31: 29330 | C31: 26356 | D31: 29373 | E31: 30485 | F31: 37163 | G31: 31762 | H31: 30964 | I31: 33988
A32: Other assets (incl. cash, receivables) | B32: 71318 | C32: 71937 | D32: 78672 | E32: 87936 | F32: 83947 | G32: 92542 | H32: 103086 | I32: 113171
A33: Total assets | B33: =SUM(B29:B32) | C33: =SUM(C29:C32) | D33: =SUM(D29:D32) | E33: =SUM(E29:E32) | F33: =SUM(F29:F32) | G33: =SUM(G29:G32) | H33: =SUM(H29:H32) | I33: =SUM(I29:I32)
A34: Balance check (must be ~0) | B34: =B28-B33 | C34: =C28-C33 | D34: =D28-D33 | E34: =E28-E33 | F34: =F28-F33 | G34: =G28-G33 | H34: =H28-H33 | I34: =I28-I33
A36: Cash Flow Statement
A37: Cash flow from operations | B37: 28593 | C37: 32369 | D37: 38802 | E37: 39949 | F37: 41965 | G37: 44338 | H37: 48908 | I37: 52094
A38: Cash flow from investing | B38: 1645 | C38: 8968 | D38: -7956 | E38: -738 | F38: 548 | G38: 6091 | H38: -2144 | I38: -11886
A39: Cash flow from financing | B39: -27897 | C39: -39915 | D39: -32634 | E39: -33581 | F39: -47878 | G39: -48536 | H39: -47438 | I39: -42133
A40: Net change in cash | B40: =SUM(B37:B39) | C40: =SUM(C37:C39) | D40: =SUM(D37:D39) | E40: =SUM(E37:E39) | F40: =SUM(F37:F39) | G40: =SUM(G37:G39) | H40: =SUM(H37:H39) | I40: =SUM(I37:I39)
A41: Free cash flow (CFO − capex) | B41: 26461 | C41: 29281 | D41: 35663 | E41: 36985 | F41: 38902 | G41: 41688 | H41: 44994 | I41: 48013
A42: FCF conversion (% of PAT) | B42: =B41/B17 | C42: =C41/C17 | D42: =D41/D17 | E42: =E41/E17 | F42: =F41/F17 | G42: =G41/G17 | H42: =H41/H17 | I42: =I41/I17

Sheet Forecast
A1: Tata Consultancy Services Ltd — 5-Year Operating Forecast & FCFF Build
A3: ₹ Crore. Drivers feed from Assumptions sheet.
A4: Fiscal Year (ends March) | B4: FY2026A | C4: FY2027E | D4: FY2028E | E4: FY2029E | F4: FY2030E | G4: FY2031E
A5: Revenue | B5: =Historical!I6 | C5: =B5*(1+Assumptions!B13) | D5: =C5*(1+Assumptions!C13) | E5: =D5*(1+Assumptions!D13) | F5: =E5*(1+Assumptions!E13) | G5: =F5*(1+Assumptions!F13)
A6: Revenue growth (%) | C6: =C5/B5-1 | D6: =D5/C5-1 | E6: =E5/D5-1 | F6: =F5/E5-1 | G6: =G5/F5-1
A7: EBITDA | B7: =Historical!I9 | C7: =C5*Assumptions!B14 | D7: =D5*Assumptions!C14 | E7: =E5*Assumptions!D14 | F7: =F5*Assumptions!E14 | G7: =G5*Assumptions!F14
A8: EBITDA margin (%) | B8: =B7/B5 | C8: =C7/C5 | D8: =D7/D5 | E8: =E7/E5 | F8: =F7/F5 | G8: =G7/G5
A9: Less: Depreciation & amortisation | C9: =C5*Assumptions!$B$15 | D9: =D5*Assumptions!$B$15 | E9: =E5*Assumptions!$B$15 | F9: =F5*Assumptions!$B$15 | G9: =G5*Assumptions!$B$15
A10: EBIT | C10: =C7-C9 | D10: =D7-D9 | E10: =E7-E9 | F10: =F7-F9 | G10: =G7-G9
A11: Less: Tax on EBIT | C11: =C10*Assumptions!$B$17 | D11: =D10*Assumptions!$B$17 | E11: =E10*Assumptions!$B$17 | F11: =F10*Assumptions!$B$17 | G11: =G10*Assumptions!$B$17
A12: NOPAT | C12: =C10-C11 | D12: =D10-D11 | E12: =E10-E11 | F12: =F10-F11 | G12: =G10-G11
A13: Add: Depreciation & amortisation | C13: =C9 | D13: =D9 | E13: =E9 | F13: =F9 | G13: =G9
A14: Less: Capex | C14: =C5*Assumptions!$B$16 | D14: =D5*Assumptions!$B$16 | E14: =E5*Assumptions!$B$16 | F14: =F5*Assumptions!$B$16 | G14: =G5*Assumptions!$B$16
A15: Less: Increase in working capital | C15: =(C5-B5)*Assumptions!$B$18 | D15: =(D5-C5)*Assumptions!$B$18 | E15: =(E5-D5)*Assumptions!$B$18 | F15: =(F5-E5)*Assumptions!$B$18 | G15: =(G5-F5)*Assumptions!$B$18
A16: Free cash flow to firm (FCFF) | C16: =C12+C13-C14-C15 | D16: =D12+D13-D14-D15 | E16: =E12+E13-E14-E15 | F16: =F12+F13-F14-F15 | G16: =G12+G13-G14-G15

Sheet DCF
A1: Tata Consultancy Services Ltd — Discounted Cash Flow Valuation
A3: ₹ Crore unless stated. WACC and terminal growth from Assumptions.
A4: Fiscal Year (ends March) | B4: FY2027E | C4: FY2028E | D4: FY2029E | E4: FY2030E | F4: FY2031E
A5: FCFF | B5: =Forecast!C16 | C5: =Forecast!D16 | D5: =Forecast!E16 | E5: =Forecast!F16 | F5: =Forecast!G16
A6: Discount period (years) | B6: 1 | C6: 2 | D6: 3 | E6: 4 | F6: 5
A7: Discount factor @ WACC | B7: =1/(1+Assumptions!$B$25)^B6 | C7: =1/(1+Assumptions!$B$25)^C6 | D7: =1/(1+Assumptions!$B$25)^D6 | E7: =1/(1+Assumptions!$B$25)^E6 | F7: =1/(1+Assumptions!$B$25)^F6
A8: PV of FCFF | B8: =B5*B7 | C8: =C5*C7 | D8: =D5*D7 | E8: =E5*E7 | F8: =F5*F7
A10: Valuation Bridge
A11: Sum of PV of explicit FCFF | B11: =SUM(B8:F8)
A12: Terminal value (Gordon growth) | B12: =F5*(1+Assumptions!B26)/(Assumptions!B25-Assumptions!B26)
A13: PV of terminal value | B13: =B12*F7
A14: Enterprise value | B14: =B11+B13
A15: Less: Net debt / add: net cash | B15: =-Assumptions!B8
A16: Equity value | B16: =B14+B15
A17: Shares outstanding (Cr) | B17: =Assumptions!B6
A18: Intrinsic value per share (₹) | B18: =B16/B17
A19: Current market price (₹) | B19: =Assumptions!B5
A20: Upside / (downside) | B20: =B18/B19-1
A21: Implied rating | B21: =IF(B20>0.12,"BUY",IF(B20>0.05,"ACCUMULATE",IF(B20>-0.05,"HOLD","REDUCE")))
A22: % of EV in terminal value | B22: =B13/B14
A24: Sensitivity: Intrinsic Value per Share (₹) — WACC vs Terminal Growth
A25: WACC ↓ / Terminal g → | B25: 0.04 | C25: 0.045 | D25: 0.05 | E25: 0.055 | F25: 0.06
A26: 0.10375 | B26: =(Forecast!C16/(1+$A26)^1+Forecast!D16/(1+$A26)^2+Forecast!E16/(1+$A26)^3+Forecast!F16/(1+$A26)^4+Forecast!G16/(1+$A26)^5+Forecast!G16*(1+B$25)/($A26-B$25)/(1+$A26)^5-Assumptions!$B$8)/Assumptions!$B$6 | C26: =(Forecast!C16/(1+$A26)^1+Forecast!D16/(1+$A26)^2+Forecast!E16/(1+$A26)^3+Forecast!F16/(1+$A26)^4+Forecast!G16/(1+$A26)^5+Forecast!G16*(1+C$25)/($A26-C$25)/(1+$A26)^5-Assumptions!$B$8)/Assumptions!$B$6 | D26: =(Forecast!C16/(1+$A26)^1+Forecast!D16/(1+$A26)^2+Forecast!E16/(1+$A26)^3+Forecast!F16/(1+$A26)^4+Forecast!G16/(1+$A26)^5+Forecast!G16*(1+D$25)/($A26-D$25)/(1+$A26)^5-Assumptions!$B$8)/Assumptions!$B$6 | E26: =(Forecast!C16/(1+$A26)^1+Forecast!D16/(1+$A26)^2+Forecast!E16/(1+$A26)^3+Forecast!F16/(1+$A26)^4+Forecast!G16/(1+$A26)^5+Forecast!G16*(1+E$25)/($A26-E$25)/(1+$A26)^5-Assumptions!$B$8)/Assumptions!$B$6 | F26: =(Forecast!C16/(1+$A26)^1+Forecast!D16/(1+$A26)^2+Forecast!E16/(1+$A26)^3+Forecast!F16/(1+$A26)^4+Forecast!G16/(1+$A26)^5+Forecast!G16*(1+F$25)/($A26-F$25)/(1+$A26)^5-Assumptions!$B$8)/Assumptions!$B$6
A27: 0.10875 | B27: =(Forecast!C16/(1+$A27)^1+Forecast!D16/(1+$A27)^2+Forecast!E16/(1+$A27)^3+Forecast!F16/(1+$A27)^4+Forecast!G16/(1+$A27)^5+Forecast!G16*(1+B$25)/($A27-B$25)/(1+$A27)^5-Assumptions!$B$8)/Assumptions!$B$6 | C27: =(Forecast!C16/(1+$A27)^1+Forecast!D16/(1+$A27)^2+Forecast!E16/(1+$A27)^3+Forecast!F16/(1+$A27)^4+Forecast!G16/(1+$A27)^5+Forecast!G16*(1+C$25)/($A27-C$25)/(1+$A27)^5-Assumptions!$B$8)/Assumptions!$B$6 | D27: =(Forecast!C16/(1+$A27)^1+Forecast!D16/(1+$A27)^2+Forecast!E16/(1+$A27)^3+Forecast!F16/(1+$A27)^4+Forecast!G16/(1+$A27)^5+Forecast!G16*(1+D$25)/($A27-D$25)/(1+$A27)^5-Assumptions!$B$8)/Assumptions!$B$6 | E27: =(Forecast!C16/(1+$A27)^1+Forecast!D16/(1+$A27)^2+Forecast!E16/(1+$A27)^3+Forecast!F16/(1+$A27)^4+Forecast!G16/(1+$A27)^5+Forecast!G16*(1+E$25)/($A27-E$25)/(1+$A27)^5-Assumptions!$B$8)/Assumptions!$B$6 | F27: =(Forecast!C16/(1+$A27)^1+Forecast!D16/(1+$A27)^2+Forecast!E16/(1+$A27)^3+Forecast!F16/(1+$A27)^4+Forecast!G16/(1+$A27)^5+Forecast!G16*(1+F$25)/($A27-F$25)/(1+$A27)^5-Assumptions!$B$8)/Assumptions!$B$6
A28: 0.11375 | B28: =(Forecast!C16/(1+$A28)^1+Forecast!D16/(1+$A28)^2+Forecast!E16/(1+$A28)^3+Forecast!F16/(1+$A28)^4+Forecast!G16/(1+$A28)^5+Forecast!G16*(1+B$25)/($A28-B$25)/(1+$A28)^5-Assumptions!$B$8)/Assumptions!$B$6 | C28: =(Forecast!C16/(1+$A28)^1+Forecast!D16/(1+$A28)^2+Forecast!E16/(1+$A28)^3+Forecast!F16/(1+$A28)^4+Forecast!G16/(1+$A28)^5+Forecast!G16*(1+C$25)/($A28-C$25)/(1+$A28)^5-Assumptions!$B$8)/Assumptions!$B$6 | D28: =(Forecast!C16/(1+$A28)^1+Forecast!D16/(1+$A28)^2+Forecast!E16/(1+$A28)^3+Forecast!F16/(1+$A28)^4+Forecast!G16/(1+$A28)^5+Forecast!G16*(1+D$25)/($A28-D$25)/(1+$A28)^5-Assumptions!$B$8)/Assumptions!$B$6 | E28: =(Forecast!C16/(1+$A28)^1+Forecast!D16/(1+$A28)^2+Forecast!E16/(1+$A28)^3+Forecast!F16/(1+$A28)^4+Forecast!G16/(1+$A28)^5+Forecast!G16*(1+E$25)/($A28-E$25)/(1+$A28)^5-Assumptions!$B$8)/Assumptions!$B$6 | F28: =(Forecast!C16/(1+$A28)^1+Forecast!D16/(1+$A28)^2+Forecast!E16/(1+$A28)^3+Forecast!F16/(1+$A28)^4+Forecast!G16/(1+$A28)^5+Forecast!G16*(1+F$25)/($A28-F$25)/(1+$A28)^5-Assumptions!$B$8)/Assumptions!$B$6
A29: 0.11875 | B29: =(Forecast!C16/(1+$A29)^1+Forecast!D16/(1+$A29)^2+Forecast!E16/(1+$A29)^3+Forecast!F16/(1+$A29)^4+Forecast!G16/(1+$A29)^5+Forecast!G16*(1+B$25)/($A29-B$25)/(1+$A29)^5-Assumptions!$B$8)/Assumptions!$B$6 | C29: =(Forecast!C16/(1+$A29)^1+Forecast!D16/(1+$A29)^2+Forecast!E16/(1+$A29)^3+Forecast!F16/(1+$A29)^4+Forecast!G16/(1+$A29)^5+Forecast!G16*(1+C$25)/($A29-C$25)/(1+$A29)^5-Assumptions!$B$8)/Assumptions!$B$6 | D29: =(Forecast!C16/(1+$A29)^1+Forecast!D16/(1+$A29)^2+Forecast!E16/(1+$A29)^3+Forecast!F16/(1+$A29)^4+Forecast!G16/(1+$A29)^5+Forecast!G16*(1+D$25)/($A29-D$25)/(1+$A29)^5-Assumptions!$B$8)/Assumptions!$B$6 | E29: =(Forecast!C16/(1+$A29)^1+Forecast!D16/(1+$A29)^2+Forecast!E16/(1+$A29)^3+Forecast!F16/(1+$A29)^4+Forecast!G16/(1+$A29)^5+Forecast!G16*(1+E$25)/($A29-E$25)/(1+$A29)^5-Assumptions!$B$8)/Assumptions!$B$6 | F29: =(Forecast!C16/(1+$A29)^1+Forecast!D16/(1+$A29)^2+Forecast!E16/(1+$A29)^3+Forecast!F16/(1+$A29)^4+Forecast!G16/(1+$A29)^5+Forecast!G16*(1+F$25)/($A29-F$25)/(1+$A29)^5-Assumptions!$B$8)/Assumptions!$B$6
A30: 0.12375 | B30: =(Forecast!C16/(1+$A30)^1+Forecast!D16/(1+$A30)^2+Forecast!E16/(1+$A30)^3+Forecast!F16/(1+$A30)^4+Forecast!G16/(1+$A30)^5+Forecast!G16*(1+B$25)/($A30-B$25)/(1+$A30)^5-Assumptions!$B$8)/Assumptions!$B$6 | C30: =(Forecast!C16/(1+$A30)^1+Forecast!D16/(1+$A30)^2+Forecast!E16/(1+$A30)^3+Forecast!F16/(1+$A30)^4+Forecast!G16/(1+$A30)^5+Forecast!G16*(1+C$25)/($A30-C$25)/(1+$A30)^5-Assumptions!$B$8)/Assumptions!$B$6 | D30: =(Forecast!C16/(1+$A30)^1+Forecast!D16/(1+$A30)^2+Forecast!E16/(1+$A30)^3+Forecast!F16/(1+$A30)^4+Forecast!G16/(1+$A30)^5+Forecast!G16*(1+D$25)/($A30-D$25)/(1+$A30)^5-Assumptions!$B$8)/Assumptions!$B$6 | E30: =(Forecast!C16/(1+$A30)^1+Forecast!D16/(1+$A30)^2+Forecast!E16/(1+$A30)^3+Forecast!F16/(1+$A30)^4+Forecast!G16/(1+$A30)^5+Forecast!G16*(1+E$25)/($A30-E$25)/(1+$A30)^5-Assumptions!$B$8)/Assumptions!$B$6 | F30: =(Forecast!C16/(1+$A30)^1+Forecast!D16/(1+$A30)^2+Forecast!E16/(1+$A30)^3+Forecast!F16/(1+$A30)^4+Forecast!G16/(1+$A30)^5+Forecast!G16*(1+F$25)/($A30-F$25)/(1+$A30)^5-Assumptions!$B$8)/Assumptions!$B$6

Sheet Ratios
A1: Tata Consultancy Services Ltd — Ratio & Trend Analysis
A3: Computed from Historical sheet (₹ Crore basis).
A4: Fiscal Year (ends March) | B4: FY2019 | C4: FY2020 | D4: FY2021 | E4: FY2022 | F4: FY2023 | G4: FY2024 | H4: FY2025 | I4: FY2026
A5: Revenue growth (%) | B5: — | C5: =Historical!C6/Historical!B6-1 | D5: =Historical!D6/Historical!C6-1 | E5: =Historical!E6/Historical!D6-1 | F5: =Historical!F6/Historical!E6-1 | G5: =Historical!G6/Historical!F6-1 | H5: =Historical!H6/Historical!G6-1 | I5: =Historical!I6/Historical!H6-1
A6: EBITDA margin (%) | B6: =Historical!B9/Historical!B6 | C6: =Historical!C9/Historical!C6 | D6: =Historical!D9/Historical!D6 | E6: =Historical!E9/Historical!E6 | F6: =Historical!F9/Historical!F6 | G6: =Historical!G9/Historical!G6 | H6: =Historical!H9/Historical!H6 | I6: =Historical!I9/Historical!I6
A7: EBIT margin (%) | B7: =Historical!B12/Historical!B6 | C7: =Historical!C12/Historical!C6 | D7: =Historical!D12/Historical!D6 | E7: =Historical!E12/Historical!E6 | F7: =Historical!F12/Historical!F6 | G7: =Historical!G12/Historical!G6 | H7: =Historical!H12/Historical!H6 | I7: =Historical!I12/Historical!I6
A8: PAT margin (%) | B8: =Historical!B17/Historical!B6 | C8: =Historical!C17/Historical!C6 | D8: =Historical!D17/Historical!D6 | E8: =Historical!E17/Historical!E6 | F8: =Historical!F17/Historical!F6 | G8: =Historical!G17/Historical!G6 | H8: =Historical!H17/Historical!H6 | I8: =Historical!I17/Historical!I6
A9: EPS growth (%) | B9: — | C9: =Historical!C19/Historical!B19-1 | D9: =Historical!D19/Historical!C19-1 | E9: =Historical!E19/Historical!D19-1 | F9: =Historical!F19/Historical!E19-1 | G9: =Historical!G19/Historical!F19-1 | H9: =Historical!H19/Historical!G19-1 | I9: =Historical!I19/Historical!H19-1
A10: Return on equity (PAT / avg net worth) | B10: =Historical!B17/Historical!B25 | C10: =Historical!C17/((Historical!C25+Historical!B25)/2) | D10: =Historical!D17/((Historical!D25+Historical!C25)/2) | E10: =Historical!E17/((Historical!E25+Historical!D25)/2) | F10: =Historical!F17/((Historical!F25+Historical!E25)/2) | G10: =Historical!G17/((Historical!G25+Historical!F25)/2) | H10: =Historical!H17/((Historical!H25+Historical!G25)/2) | I10: =Historical!I17/((Historical!I25+Historical!H25)/2)
A11: ROCE (EBIT / avg capital employed) | B11: =Historical!B12/(Historical!B25+Historical!B26) | C11: =Historical!C12/((Historical!C25+Historical!C26+Historical!B25+Historical!B26)/2) | D11: =Historical!D12/((Historical!D25+Historical!D26+Historical!C25+Historical!C26)/2) | E11: =Historical!E12/((Historical!E25+Historical!E26+Historical!D25+Historical!D26)/2) | F11: =Historical!F12/((Historical!F25+Historical!F26+Historical!E25+Historical!E26)/2) | G11: =Historical!G12/((Historical!G25+Historical!G26+Historical!F25+Historical!F26)/2) | H11: =Historical!H12/((Historical!H25+Historical!H26+Historical!G25+Historical!G26)/2) | I11: =Historical!I12/((Historical!I25+Historical!I26+Historical!H25+Historical!H26)/2)
A12: FCF conversion (FCF / PAT) | B12: =Historical!B41/Historical!B17 | C12: =Historical!C41/Historical!C17 | D12: =Historical!D41/Historical!D17 | E12: =Historical!E41/Historical!E17 | F12: =Historical!F41/Historical!F17 | G12: =Historical!G41/Historical!G17 | H12: =Historical!H41/Historical!H17 | I12: =Historical!I41/Historical!I17
A13: Net debt / EBITDA (x) | B13: =(Historical!B26-Historical!B31)/Historical!B9 | C13: =(Historical!C26-Historical!C31)/Historical!C9 | D13: =(Historical!D26-Historical!D31)/Historical!D9 | E13: =(Historical!E26-Historical!E31)/Historical!E9 | F13: =(Historical!F26-Historical!F31)/Historical!F9 | G13: =(Historical!G26-Historical!G31)/Historical!G9 | H13: =(Historical!H26-Historical!H31)/Historical!H9 | I13: =(Historical!I26-Historical!I31)/Historical!I9
A14: Dividend payout (%) | B14: =Historical!B20 | C14: =Historical!C20 | D14: =Historical!D20 | E14: =Historical!E20 | F14: =Historical!F20 | G14: =Historical!G20 | H14: =Historical!H20 | I14: =Historical!I20

Sheet Peer Comps
A1: Tata Consultancy Services Ltd — Peer Comparison (Indian IT Services)
A3: Blue = inputs (as researched, Jun 2026). Yellow = update with live data.
A4: Company | B4: Price (₹) | C4: EPS FY26 (₹) | D4: BVPS (₹) | E4: PAT FY26 (₹ Cr) | F4: P/E (x) | G4: P/B (x)
A5: Tata Consultancy Services | B5: 2190 | C5: 134 | D5: 296 | E5: 49454 | F5: =IF(C5>0,B5/C5,"n/a") | G5: =IF(D5>0,B5/D5,"n/a")
A6: Infosys | B6: 1211 | C6: 72.59 | D6: 229 | E6: 29474 | F6: =IF(C6>0,B6/C6,"n/a") | G6: =IF(D6>0,B6/D6,"n/a")
A7: HCL Technologies | B7: 1117.6 | C7: 61.4 | D7: 257 | F7: =IF(C7>0,B7/C7,"n/a") | G7: =IF(D7>0,B7/D7,"n/a")
A8: Wipro | B8: 240.85 | C8: 12.82 | D8: 86 | F8: =IF(C8>0,B8/C8,"n/a") | G8: =IF(D8>0,B8/D8,"n/a")
A9: Tech Mahindra | B9: 1433.55 | C9: 50.2 | D9: 256 | F9: =IF(C9>0,B9/C9,"n/a") | G9: =IF(D9>0,B9/D9,"n/a")
A11: Peer rows left blank should be completed with live market data before circulation.
A13: MARKET APPROACH — COMPARABLE COMPANY ANALYSIS
A14: Peer median P/E (x) | B14: =MEDIAN(F6:F9)
A15: Peer median P/B (x) | B15: =MEDIAN(G6:G9)
A16: Implied value — median P/E × FY26 EPS (₹) | B16: =B14*C5
A18: VALUATION TRIANGULATION — FOOTBALL FIELD (multi-method)
A19: Method | B19: Low (₹) | C19: Base (₹) | D19: High (₹)
A20: DCF (FCFF, intrinsic) | B20: =DCF!B18*0.9 | C20: =DCF!B18 | D20: =DCF!B18*1.1
A21: Comparable companies — P/E | B21: =B16*0.9 | C21: =B16 | D21: =B16*1.1
A22: EV/EBITDA | B22: =B33*0.9 | C22: =B33 | D22: =B33*1.1
A23: Blended target (70% DCF / 30% relative) | C23: =0.7*DCF!B18+0.3*AVERAGE(B16,B33)
A24: Current market price (₹) | C24: =B5
A25: Implied upside / (downside) | C25: =C23/B5-1
A26: Peer prices as of Jun 2026 (IT sector fell further in Jul; refresh before publication). TCS live 18-Jul-2026.
A28: MARKET MULTIPLE — EV/EBITDA
A29: FY26 EBITDA (₹ Cr) | B29: 72900
A30: Justified EV/EBITDA (x) — below ~16x history, above ~11x current | B30: 13
A31: Enterprise value = mult × EBITDA (₹ Cr) | B31: =B30*B29
A32: Add: net cash (₹ Cr) | B32: =-Assumptions!B8
A33: EV/EBITDA-implied value / share (₹) | B33: =(B31+B32)/Assumptions!B6
A35: CROSS-CHECK — FCF YIELD
A36: FY27E FCFF (₹ Cr) | B36: =Forecast!C16
A37: FCF yield = FCFF / market cap | B37: =B36/Assumptions!B7
